{
  "sidebarInstallation": [
    {
      "type": "category",
      "label": "Installation",
      "collapsible": true,
      "collapsed": false,
      "items": [
        "server/windows/installation",
        "server/linux/installation",
        "server/macos/installation"
      ]
    },
    {
      "type": "category",
      "label": "Sample-App",
      "collapsible": true,
      "collapsed": false,
      "items": [
        "quickstart/samples-gin",
        "quickstart/samples-mux",
        "quickstart/samples-nodejs",
        "quickstart/samples-redis",
        "quickstart/samples-django",
        "quickstart/samples-echo",
        "quickstart/samples-bunjs",
        "quickstart/samples-fastapi-twilio",
        "quickstart/samples-flask",
        "quickstart/samples-fastapi"
      ]
    }
  ],

  "sidebarExplanation": [
    {
      "type": "category",
      "label": "Explanation",
      "collapsible": true,
      "collapsed": false,
      "items": [
        "keploy-explained/introduction",
        "keploy-explained/how-keploy-works",
        "keploy-explained/why-keploy",
        "keploy-explained/faq",
        "server/index"
      ]
    },
    {
      "type": "category",
      "label": "Running Keploy",
      "collapsible": true,
      "collapsed": false,
      "items": [
        "running-keploy/rename-testcases"
      ]
    },
      {
      "type": "category",
      "label": "Hacktoberfest 2023",
      "collapsible": true,
      "collapsed": false,
      "items": [
        "hacktoberfest/contribution-guide",
        "hacktoberfest/code-contribution",
        "hacktoberfest/no-code-contribution"
      ]
    },
    {
      "type": "category",
      "label": "Resources",
      "collapsible": true,
      "collapsed": true,
      "items": [
        "concepts/general-glossary"
      ]
    }
  ],

  "sidebarContributionGuide": [
    {
      "type": "category",
      "label": "Dev Guide",
      "collapsible": false,
      "items": [
        "keploy-explained/contribution-guide",
        "keploy-explained/docs-dev-guide"
      ]
    },
    {
      "type": "category",
      "label": "Database Support",
      "collapsible": true,
      "collapsed": false,
      "items": [
        "dependencies/mongo"
      ]
    }
  ]
}
